py2nim/PythonToNim.py
py2nim/__init__.py
py2nim-0.0.1.dist-info/METADATA
py2nim-0.0.1.dist-info/WHEEL
py2nim-0.0.1.dist-info/top_level.txt
py2nim-0.0.1.dist-info/RECORD
